simple_framework/__init__.py
simple_framework/backends/BaseBackendClass.py
simple_framework/backends/__init__.py
simple_framework/backends/horovod_backend.py
simple_framework/backends/simple_backend.py
simple_framework/callbacks/BaseCallbackClass.py
simple_framework/callbacks/CallbacksHandler.py
simple_framework/callbacks/CheckpointCallback.py
simple_framework/callbacks/CsvCallback.py
simple_framework/callbacks/__init__.py
simple_framework/tests/Tests_base.py
simple_framework/tests/__init__.py
simple_framework/tests/checkpint_callback_test.py
simple_framework/tests/csv_callback_test.py
simple_framework/trainer/BaseTrainerClass.py
simple_framework/trainer/__init__.py
simple_framework/trainer/trainer.py
simple_framework/utilities/__init__.py
simple_framework/utilities/metrics.py
simple_framework/utilities/schedulers.py
simple_framework-0.0.1.8.dist-info/METADATA
simple_framework-0.0.1.8.dist-info/WHEEL
simple_framework-0.0.1.8.dist-info/top_level.txt
simple_framework-0.0.1.8.dist-info/RECORD
